{
  "plugin": "php-compatibility-checker",
  "scan_time": "2026-06-16T18:36:47+00:00",
  "summary": {
    "total_sources": 9,
    "total_sinks": 7,
    "total_sanitizers": 16,
    "direct_flows": 21,
    "functions_with_sources": 3,
    "functions_with_sinks": 3,
    "files_analyzed": 3,
    "parse_errors": 0
  },
  "sources": [
    {
      "file": "lib/class-php-compatibility-checker.php",
      "line": 153,
      "class": "PHP_Compatibility_Checker",
      "function": "get_plugins_to_scan",
      "kind": "get_option",
      "category": "database_reads",
      "expression": "get_option( 'active_plugins' )"
    },
    {
      "file": "lib/class-php-compatibility-checker.php",
      "line": 174,
      "class": "PHP_Compatibility_Checker",
      "function": "get_plugins_to_scan",
      "kind": "get_site_transient",
      "category": "database_reads",
      "expression": "get_site_transient( 'update_plugins' )"
    },
    {
      "file": "lib/class-php-compatibility-checker.php",
      "line": 193,
      "class": "PHP_Compatibility_Checker",
      "function": "get_plugins_to_scan",
      "kind": "sanitize_title",
      "category": "wordpress_input_functions",
      "expression": "sanitize_title( $plugin['slug'] )"
    },
    {
      "file": "lib/class-php-compatibility-checker.php",
      "line": 194,
      "class": "PHP_Compatibility_Checker",
      "function": "get_plugins_to_scan",
      "kind": "sanitize_text_field",
      "category": "wordpress_input_functions",
      "expression": "sanitize_text_field( $plugin['Name'] )"
    },
    {
      "file": "lib/class-php-compatibility-checker.php",
      "line": 195,
      "class": "PHP_Compatibility_Checker",
      "function": "get_plugins_to_scan",
      "kind": "sanitize_text_field",
      "category": "wordpress_input_functions",
      "expression": "sanitize_text_field( $plugin['Version'] )"
    },
    {
      "file": "lib/class-php-compatibility-checker.php",
      "line": 249,
      "class": "PHP_Compatibility_Checker",
      "function": "get_themes_to_scan",
      "kind": "sanitize_title",
      "category": "wordpress_input_functions",
      "expression": "sanitize_title( $theme['id'] )"
    },
    {
      "file": "lib/class-php-compatibility-checker.php",
      "line": 250,
      "class": "PHP_Compatibility_Checker",
      "function": "get_themes_to_scan",
      "kind": "sanitize_text_field",
      "category": "wordpress_input_functions",
      "expression": "sanitize_text_field( $theme['name'] )"
    },
    {
      "file": "lib/class-php-compatibility-checker.php",
      "line": 251,
      "class": "PHP_Compatibility_Checker",
      "function": "get_themes_to_scan",
      "kind": "sanitize_text_field",
      "category": "wordpress_input_functions",
      "expression": "sanitize_text_field( $theme['version'] )"
    },
    {
      "file": "wpengine-phpcompat.php",
      "line": 100,
      "class": null,
      "function": "maybe_migrate_to_wptide",
      "kind": "get_option",
      "category": "database_reads",
      "expression": "get_option( 'wpephpcompat_is_wptide', false )"
    }
  ],
  "sinks": [
    {
      "file": "lib/class-php-compatibility-checker.php",
      "line": 142,
      "class": "PHP_Compatibility_Checker",
      "function": "get_plugins_to_scan",
      "kind": "array_filter",
      "category": "code_execution",
      "expression": "array_filter(\n\t\t\t$plugins,\n\t\t\tfunction ( $plugin_data ) use ( $excluded_plugins ) {\n\t\t\t\treturn ! in_array( $plugin_data['Name'], $excluded_plugins, true );\n\t\t\t}\n\t\t)"
    },
    {
      "file": "lib/class-php-compatibility-checker.php",
      "line": 164,
      "class": "PHP_Compatibility_Checker",
      "function": "get_plugins_to_scan",
      "kind": "array_map",
      "category": "code_execution",
      "expression": "array_map(\n\t\t\tfunction( $plugin_file, $plugin_data ) use ( $active_plugins ) {\n\t\t\t\t$plugin_data['plugin_file'] = $plugin_file;\n\t\t\t\t$plugin_data['active']      = in_array( $plugin_file, $active_plugins, true ) ? 'yes' : 'no';\n\t\t\t\treturn $plugin_data;\n\t\t\t},\n\t\t\tarray_keys( $plugins ),\n\t\t\t$plugins\n\t\t)"
    },
    {
      "file": "lib/class-php-compatibility-checker.php",
      "line": 190,
      "class": "PHP_Compatibility_Checker",
      "function": "get_plugins_to_scan",
      "kind": "array_map",
      "category": "code_execution",
      "expression": "array_map(\n\t\t\tfunction( $plugin ) {\n\t\t\t\treturn array(\n\t\t\t\t\t'slug'    => sanitize_title( $plugin['slug'] ),\n\t\t\t\t\t'name'    => sanitize_text_field( $plugin['Name'] ),\n\t\t\t\t\t'version' => sanitize_text_field( $plugin['Version'] ),\n\t\t\t\t\t'active'  => $plugin['active'],\n\t\t\t\t);\n\t\t\t},\n\t\t\t$plugins\n\t\t)"
    },
    {
      "file": "lib/class-php-compatibility-checker.php",
      "line": 239,
      "class": "PHP_Compatibility_Checker",
      "function": "get_themes_to_scan",
      "kind": "array_filter",
      "category": "code_execution",
      "expression": "array_filter(\n\t\t\t$themes_data,\n\t\t\tfunction ( $theme_data ) use ( $excluded_themes ) {\n\t\t\t\treturn ! in_array( $theme_data['name'], $excluded_themes, true );\n\t\t\t}\n\t\t)"
    },
    {
      "file": "lib/class-php-compatibility-checker.php",
      "line": 246,
      "class": "PHP_Compatibility_Checker",
      "function": "get_themes_to_scan",
      "kind": "array_map",
      "category": "code_execution",
      "expression": "array_map(\n\t\t\tfunction( $theme ) {\n\t\t\t\treturn array(\n\t\t\t\t\t'slug'    => sanitize_title( $theme['id'] ),\n\t\t\t\t\t'name'    => sanitize_text_field( $theme['name'] ),\n\t\t\t\t\t'version' => sanitize_text_field( $theme['version'] ),\n\t\t\t\t\t'active'  => true === $theme['active'] ? 'yes' : 'no',\n\t\t\t\t);\n\t\t\t},\n\t\t\t$themes_data\n\t\t)"
    },
    {
      "file": "lib/class-php-compatibility-checker.php",
      "line": 368,
      "class": "PHP_Compatibility_Checker",
      "function": "scan_page",
      "kind": "printf",
      "category": "xss_output",
      "expression": "printf(\n\t\t\t\t\t\t\t/* translators: %s: hosting URL */\n\t\t\t\t\t\t\twp_kses_post( __( '<strong>Attention:</strong> Not all errors are show-stoppers. <a target=\"_blank\" href=\"%s\">Use LocalWP to test this site on PHP 8</a> to see if it just works!', 'wpe-php-compat' ) ),\n\t\t\t\t\t\t\tesc_url( 'https://localwp.com/' )\n\t\t\t\t\t\t)"
    },
    {
      "file": "lib/class-php-compatibility-checker.php",
      "line": 386,
      "class": "PHP_Compatibility_Checker",
      "function": "scan_page",
      "kind": "printf",
      "category": "xss_output",
      "expression": "printf(\n\t\t\t\t\t\t\t\t/* translators: %s: GitHub Wiki URL */\n\t\t\t\t\t\t\t\twp_kses_post( __( 'Report false positives <a target=\"_blank\" href=\"%s\">on our GitHub repo</a>.', 'wpe-php-compat' ) ),\n\t\t\t\t\t\t\t\t'https://github.com/wpengine/phpcompat/wiki/Results'\n\t\t\t\t\t\t\t)"
    }
  ],
  "sanitizers": [
    {
      "file": "lib/class-php-compatibility-checker.php",
      "line": 62,
      "class": "PHP_Compatibility_Checker",
      "function": "enqueue_scripts",
      "kind": "wp_kses_post",
      "category": "xss",
      "expression": "wp_kses_post( __( 'Looks like you are using a development version of <strong>PHP Compatibility Checker</strong>. Please run <code>make build</code> to build assets.', 'wpe-php-compat' ) )"
    },
    {
      "file": "lib/class-php-compatibility-checker.php",
      "line": 298,
      "class": "PHP_Compatibility_Checker",
      "function": "scan_page",
      "kind": "esc_url",
      "category": "xss",
      "expression": "esc_url( 'https://wpeng.in/5a0336/' )"
    },
    {
      "file": "lib/class-php-compatibility-checker.php",
      "line": 299,
      "class": "PHP_Compatibility_Checker",
      "function": "scan_page",
      "kind": "esc_url",
      "category": "xss",
      "expression": "esc_url( 'https://wpeng.in/fa14e4/' )"
    },
    {
      "file": "lib/class-php-compatibility-checker.php",
      "line": 300,
      "class": "PHP_Compatibility_Checker",
      "function": "scan_page",
      "kind": "esc_url",
      "category": "xss",
      "expression": "esc_url( 'https://wpeng.in/407b79/' )"
    },
    {
      "file": "lib/class-php-compatibility-checker.php",
      "line": 301,
      "class": "PHP_Compatibility_Checker",
      "function": "scan_page",
      "kind": "esc_url",
      "category": "xss",
      "expression": "esc_url( 'https://wpeng.in/22f22b/' )"
    },
    {
      "file": "lib/class-php-compatibility-checker.php",
      "line": 302,
      "class": "PHP_Compatibility_Checker",
      "function": "scan_page",
      "kind": "esc_url",
      "category": "xss",
      "expression": "esc_url( 'https://codeable.io/wp-admin/admin-ajax.php?action=wp_engine_phpcompat' )"
    },
    {
      "file": "lib/class-php-compatibility-checker.php",
      "line": 370,
      "class": "PHP_Compatibility_Checker",
      "function": "scan_page",
      "kind": "wp_kses_post",
      "category": "xss",
      "expression": "wp_kses_post( __( '<strong>Attention:</strong> Not all errors are show-stoppers. <a target=\"_blank\" href=\"%s\">Use LocalWP to test this site on PHP 8</a> to see if it just works!', 'wpe-php-compat' ) )"
    },
    {
      "file": "lib/class-php-compatibility-checker.php",
      "line": 371,
      "class": "PHP_Compatibility_Checker",
      "function": "scan_page",
      "kind": "esc_url",
      "category": "xss",
      "expression": "esc_url( 'https://localwp.com/' )"
    },
    {
      "file": "lib/class-php-compatibility-checker.php",
      "line": 388,
      "class": "PHP_Compatibility_Checker",
      "function": "scan_page",
      "kind": "wp_kses_post",
      "category": "xss",
      "expression": "wp_kses_post( __( 'Report false positives <a target=\"_blank\" href=\"%s\">on our GitHub repo</a>.', 'wpe-php-compat' ) )"
    },
    {
      "file": "lib/class-php-compatibility-checker.php",
      "line": 399,
      "class": "PHP_Compatibility_Checker",
      "function": "scan_page",
      "kind": "esc_url",
      "category": "xss",
      "expression": "esc_url( $url_wpe_logo )"
    },
    {
      "file": "lib/class-php-compatibility-checker.php",
      "line": 412,
      "class": "PHP_Compatibility_Checker",
      "function": "scan_page",
      "kind": "esc_url",
      "category": "xss",
      "expression": "esc_url( $url_wpe_customer_upgrade )"
    },
    {
      "file": "lib/class-php-compatibility-checker.php",
      "line": 414,
      "class": "PHP_Compatibility_Checker",
      "function": "scan_page",
      "kind": "esc_url",
      "category": "xss",
      "expression": "esc_url( $url_get_hosting )"
    },
    {
      "file": "lib/class-php-compatibility-checker.php",
      "line": 415,
      "class": "PHP_Compatibility_Checker",
      "function": "scan_page",
      "kind": "esc_url",
      "category": "xss",
      "expression": "esc_url( $url_wpe_customer_upgrade )"
    },
    {
      "file": "lib/class-php-compatibility-checker.php",
      "line": 427,
      "class": "PHP_Compatibility_Checker",
      "function": "scan_page",
      "kind": "esc_url",
      "category": "xss",
      "expression": "esc_url( $url_wpe_agency_partners )"
    },
    {
      "file": "lib/class-php-compatibility-checker.php",
      "line": 433,
      "class": "PHP_Compatibility_Checker",
      "function": "scan_page",
      "kind": "esc_url",
      "category": "xss",
      "expression": "esc_url( add_query_arg( array( 'action' => 'wp_engine_phpcompat' ), $url_codeable_submit ) )"
    },
    {
      "file": "lib/class-php-compatibility-checker.php",
      "line": 510,
      "class": "PHP_Compatibility_Checker",
      "function": "filter_plugin_links",
      "kind": "esc_url",
      "category": "xss",
      "expression": "esc_url( $url )"
    }
  ],
  "flows": [
    {
      "source": {
        "file": "lib/class-php-compatibility-checker.php",
        "line": 153,
        "kind": "get_option",
        "category": "database_reads",
        "expression": "get_option( 'active_plugins' )"
      },
      "sink": {
        "file": "lib/class-php-compatibility-checker.php",
        "line": 142,
        "kind": "array_filter",
        "category": "code_execution",
        "expression": "array_filter(\n\t\t\t$plugins,\n\t\t\tfunction ( $plugin_data ) use ( $excluded_plugins ) {\n\t\t\t\treturn ! in_array( $plugin_data['Name'], $excluded_plugins, true );\n\t\t\t}\n\t\t)"
      },
      "function": "get_plugins_to_scan",
      "class": "PHP_Compatibility_Checker"
    },
    {
      "source": {
        "file": "lib/class-php-compatibility-checker.php",
        "line": 153,
        "kind": "get_option",
        "category": "database_reads",
        "expression": "get_option( 'active_plugins' )"
      },
      "sink": {
        "file": "lib/class-php-compatibility-checker.php",
        "line": 164,
        "kind": "array_map",
        "category": "code_execution",
        "expression": "array_map(\n\t\t\tfunction( $plugin_file, $plugin_data ) use ( $active_plugins ) {\n\t\t\t\t$plugin_data['plugin_file'] = $plugin_file;\n\t\t\t\t$plugin_data['active']      = in_array( $plugin_file, $active_plugins, true ) ? 'yes' : 'no';\n\t\t\t\treturn $plugin_data;\n\t\t\t},\n\t\t\tarray_keys( $plugins ),\n\t\t\t$plugins\n\t\t)"
      },
      "function": "get_plugins_to_scan",
      "class": "PHP_Compatibility_Checker"
    },
    {
      "source": {
        "file": "lib/class-php-compatibility-checker.php",
        "line": 153,
        "kind": "get_option",
        "category": "database_reads",
        "expression": "get_option( 'active_plugins' )"
      },
      "sink": {
        "file": "lib/class-php-compatibility-checker.php",
        "line": 190,
        "kind": "array_map",
        "category": "code_execution",
        "expression": "array_map(\n\t\t\tfunction( $plugin ) {\n\t\t\t\treturn array(\n\t\t\t\t\t'slug'    => sanitize_title( $plugin['slug'] ),\n\t\t\t\t\t'name'    => sanitize_text_field( $plugin['Name'] ),\n\t\t\t\t\t'version' => sanitize_text_field( $plugin['Version'] ),\n\t\t\t\t\t'active'  => $plugin['active'],\n\t\t\t\t);\n\t\t\t},\n\t\t\t$plugins\n\t\t)"
      },
      "function": "get_plugins_to_scan",
      "class": "PHP_Compatibility_Checker"
    },
    {
      "source": {
        "file": "lib/class-php-compatibility-checker.php",
        "line": 174,
        "kind": "get_site_transient",
        "category": "database_reads",
        "expression": "get_site_transient( 'update_plugins' )"
      },
      "sink": {
        "file": "lib/class-php-compatibility-checker.php",
        "line": 142,
        "kind": "array_filter",
        "category": "code_execution",
        "expression": "array_filter(\n\t\t\t$plugins,\n\t\t\tfunction ( $plugin_data ) use ( $excluded_plugins ) {\n\t\t\t\treturn ! in_array( $plugin_data['Name'], $excluded_plugins, true );\n\t\t\t}\n\t\t)"
      },
      "function": "get_plugins_to_scan",
      "class": "PHP_Compatibility_Checker"
    },
    {
      "source": {
        "file": "lib/class-php-compatibility-checker.php",
        "line": 174,
        "kind": "get_site_transient",
        "category": "database_reads",
        "expression": "get_site_transient( 'update_plugins' )"
      },
      "sink": {
        "file": "lib/class-php-compatibility-checker.php",
        "line": 164,
        "kind": "array_map",
        "category": "code_execution",
        "expression": "array_map(\n\t\t\tfunction( $plugin_file, $plugin_data ) use ( $active_plugins ) {\n\t\t\t\t$plugin_data['plugin_file'] = $plugin_file;\n\t\t\t\t$plugin_data['active']      = in_array( $plugin_file, $active_plugins, true ) ? 'yes' : 'no';\n\t\t\t\treturn $plugin_data;\n\t\t\t},\n\t\t\tarray_keys( $plugins ),\n\t\t\t$plugins\n\t\t)"
      },
      "function": "get_plugins_to_scan",
      "class": "PHP_Compatibility_Checker"
    },
    {
      "source": {
        "file": "lib/class-php-compatibility-checker.php",
        "line": 174,
        "kind": "get_site_transient",
        "category": "database_reads",
        "expression": "get_site_transient( 'update_plugins' )"
      },
      "sink": {
        "file": "lib/class-php-compatibility-checker.php",
        "line": 190,
        "kind": "array_map",
        "category": "code_execution",
        "expression": "array_map(\n\t\t\tfunction( $plugin ) {\n\t\t\t\treturn array(\n\t\t\t\t\t'slug'    => sanitize_title( $plugin['slug'] ),\n\t\t\t\t\t'name'    => sanitize_text_field( $plugin['Name'] ),\n\t\t\t\t\t'version' => sanitize_text_field( $plugin['Version'] ),\n\t\t\t\t\t'active'  => $plugin['active'],\n\t\t\t\t);\n\t\t\t},\n\t\t\t$plugins\n\t\t)"
      },
      "function": "get_plugins_to_scan",
      "class": "PHP_Compatibility_Checker"
    },
    {
      "source": {
        "file": "lib/class-php-compatibility-checker.php",
        "line": 193,
        "kind": "sanitize_title",
        "category": "wordpress_input_functions",
        "expression": "sanitize_title( $plugin['slug'] )"
      },
      "sink": {
        "file": "lib/class-php-compatibility-checker.php",
        "line": 142,
        "kind": "array_filter",
        "category": "code_execution",
        "expression": "array_filter(\n\t\t\t$plugins,\n\t\t\tfunction ( $plugin_data ) use ( $excluded_plugins ) {\n\t\t\t\treturn ! in_array( $plugin_data['Name'], $excluded_plugins, true );\n\t\t\t}\n\t\t)"
      },
      "function": "get_plugins_to_scan",
      "class": "PHP_Compatibility_Checker"
    },
    {
      "source": {
        "file": "lib/class-php-compatibility-checker.php",
        "line": 193,
        "kind": "sanitize_title",
        "category": "wordpress_input_functions",
        "expression": "sanitize_title( $plugin['slug'] )"
      },
      "sink": {
        "file": "lib/class-php-compatibility-checker.php",
        "line": 164,
        "kind": "array_map",
        "category": "code_execution",
        "expression": "array_map(\n\t\t\tfunction( $plugin_file, $plugin_data ) use ( $active_plugins ) {\n\t\t\t\t$plugin_data['plugin_file'] = $plugin_file;\n\t\t\t\t$plugin_data['active']      = in_array( $plugin_file, $active_plugins, true ) ? 'yes' : 'no';\n\t\t\t\treturn $plugin_data;\n\t\t\t},\n\t\t\tarray_keys( $plugins ),\n\t\t\t$plugins\n\t\t)"
      },
      "function": "get_plugins_to_scan",
      "class": "PHP_Compatibility_Checker"
    },
    {
      "source": {
        "file": "lib/class-php-compatibility-checker.php",
        "line": 193,
        "kind": "sanitize_title",
        "category": "wordpress_input_functions",
        "expression": "sanitize_title( $plugin['slug'] )"
      },
      "sink": {
        "file": "lib/class-php-compatibility-checker.php",
        "line": 190,
        "kind": "array_map",
        "category": "code_execution",
        "expression": "array_map(\n\t\t\tfunction( $plugin ) {\n\t\t\t\treturn array(\n\t\t\t\t\t'slug'    => sanitize_title( $plugin['slug'] ),\n\t\t\t\t\t'name'    => sanitize_text_field( $plugin['Name'] ),\n\t\t\t\t\t'version' => sanitize_text_field( $plugin['Version'] ),\n\t\t\t\t\t'active'  => $plugin['active'],\n\t\t\t\t);\n\t\t\t},\n\t\t\t$plugins\n\t\t)"
      },
      "function": "get_plugins_to_scan",
      "class": "PHP_Compatibility_Checker"
    },
    {
      "source": {
        "file": "lib/class-php-compatibility-checker.php",
        "line": 194,
        "kind": "sanitize_text_field",
        "category": "wordpress_input_functions",
        "expression": "sanitize_text_field( $plugin['Name'] )"
      },
      "sink": {
        "file": "lib/class-php-compatibility-checker.php",
        "line": 142,
        "kind": "array_filter",
        "category": "code_execution",
        "expression": "array_filter(\n\t\t\t$plugins,\n\t\t\tfunction ( $plugin_data ) use ( $excluded_plugins ) {\n\t\t\t\treturn ! in_array( $plugin_data['Name'], $excluded_plugins, true );\n\t\t\t}\n\t\t)"
      },
      "function": "get_plugins_to_scan",
      "class": "PHP_Compatibility_Checker"
    },
    {
      "source": {
        "file": "lib/class-php-compatibility-checker.php",
        "line": 194,
        "kind": "sanitize_text_field",
        "category": "wordpress_input_functions",
        "expression": "sanitize_text_field( $plugin['Name'] )"
      },
      "sink": {
        "file": "lib/class-php-compatibility-checker.php",
        "line": 164,
        "kind": "array_map",
        "category": "code_execution",
        "expression": "array_map(\n\t\t\tfunction( $plugin_file, $plugin_data ) use ( $active_plugins ) {\n\t\t\t\t$plugin_data['plugin_file'] = $plugin_file;\n\t\t\t\t$plugin_data['active']      = in_array( $plugin_file, $active_plugins, true ) ? 'yes' : 'no';\n\t\t\t\treturn $plugin_data;\n\t\t\t},\n\t\t\tarray_keys( $plugins ),\n\t\t\t$plugins\n\t\t)"
      },
      "function": "get_plugins_to_scan",
      "class": "PHP_Compatibility_Checker"
    },
    {
      "source": {
        "file": "lib/class-php-compatibility-checker.php",
        "line": 194,
        "kind": "sanitize_text_field",
        "category": "wordpress_input_functions",
        "expression": "sanitize_text_field( $plugin['Name'] )"
      },
      "sink": {
        "file": "lib/class-php-compatibility-checker.php",
        "line": 190,
        "kind": "array_map",
        "category": "code_execution",
        "expression": "array_map(\n\t\t\tfunction( $plugin ) {\n\t\t\t\treturn array(\n\t\t\t\t\t'slug'    => sanitize_title( $plugin['slug'] ),\n\t\t\t\t\t'name'    => sanitize_text_field( $plugin['Name'] ),\n\t\t\t\t\t'version' => sanitize_text_field( $plugin['Version'] ),\n\t\t\t\t\t'active'  => $plugin['active'],\n\t\t\t\t);\n\t\t\t},\n\t\t\t$plugins\n\t\t)"
      },
      "function": "get_plugins_to_scan",
      "class": "PHP_Compatibility_Checker"
    },
    {
      "source": {
        "file": "lib/class-php-compatibility-checker.php",
        "line": 195,
        "kind": "sanitize_text_field",
        "category": "wordpress_input_functions",
        "expression": "sanitize_text_field( $plugin['Version'] )"
      },
      "sink": {
        "file": "lib/class-php-compatibility-checker.php",
        "line": 142,
        "kind": "array_filter",
        "category": "code_execution",
        "expression": "array_filter(\n\t\t\t$plugins,\n\t\t\tfunction ( $plugin_data ) use ( $excluded_plugins ) {\n\t\t\t\treturn ! in_array( $plugin_data['Name'], $excluded_plugins, true );\n\t\t\t}\n\t\t)"
      },
      "function": "get_plugins_to_scan",
      "class": "PHP_Compatibility_Checker"
    },
    {
      "source": {
        "file": "lib/class-php-compatibility-checker.php",
        "line": 195,
        "kind": "sanitize_text_field",
        "category": "wordpress_input_functions",
        "expression": "sanitize_text_field( $plugin['Version'] )"
      },
      "sink": {
        "file": "lib/class-php-compatibility-checker.php",
        "line": 164,
        "kind": "array_map",
        "category": "code_execution",
        "expression": "array_map(\n\t\t\tfunction( $plugin_file, $plugin_data ) use ( $active_plugins ) {\n\t\t\t\t$plugin_data['plugin_file'] = $plugin_file;\n\t\t\t\t$plugin_data['active']      = in_array( $plugin_file, $active_plugins, true ) ? 'yes' : 'no';\n\t\t\t\treturn $plugin_data;\n\t\t\t},\n\t\t\tarray_keys( $plugins ),\n\t\t\t$plugins\n\t\t)"
      },
      "function": "get_plugins_to_scan",
      "class": "PHP_Compatibility_Checker"
    },
    {
      "source": {
        "file": "lib/class-php-compatibility-checker.php",
        "line": 195,
        "kind": "sanitize_text_field",
        "category": "wordpress_input_functions",
        "expression": "sanitize_text_field( $plugin['Version'] )"
      },
      "sink": {
        "file": "lib/class-php-compatibility-checker.php",
        "line": 190,
        "kind": "array_map",
        "category": "code_execution",
        "expression": "array_map(\n\t\t\tfunction( $plugin ) {\n\t\t\t\treturn array(\n\t\t\t\t\t'slug'    => sanitize_title( $plugin['slug'] ),\n\t\t\t\t\t'name'    => sanitize_text_field( $plugin['Name'] ),\n\t\t\t\t\t'version' => sanitize_text_field( $plugin['Version'] ),\n\t\t\t\t\t'active'  => $plugin['active'],\n\t\t\t\t);\n\t\t\t},\n\t\t\t$plugins\n\t\t)"
      },
      "function": "get_plugins_to_scan",
      "class": "PHP_Compatibility_Checker"
    },
    {
      "source": {
        "file": "lib/class-php-compatibility-checker.php",
        "line": 249,
        "kind": "sanitize_title",
        "category": "wordpress_input_functions",
        "expression": "sanitize_title( $theme['id'] )"
      },
      "sink": {
        "file": "lib/class-php-compatibility-checker.php",
        "line": 239,
        "kind": "array_filter",
        "category": "code_execution",
        "expression": "array_filter(\n\t\t\t$themes_data,\n\t\t\tfunction ( $theme_data ) use ( $excluded_themes ) {\n\t\t\t\treturn ! in_array( $theme_data['name'], $excluded_themes, true );\n\t\t\t}\n\t\t)"
      },
      "function": "get_themes_to_scan",
      "class": "PHP_Compatibility_Checker"
    },
    {
      "source": {
        "file": "lib/class-php-compatibility-checker.php",
        "line": 249,
        "kind": "sanitize_title",
        "category": "wordpress_input_functions",
        "expression": "sanitize_title( $theme['id'] )"
      },
      "sink": {
        "file": "lib/class-php-compatibility-checker.php",
        "line": 246,
        "kind": "array_map",
        "category": "code_execution",
        "expression": "array_map(\n\t\t\tfunction( $theme ) {\n\t\t\t\treturn array(\n\t\t\t\t\t'slug'    => sanitize_title( $theme['id'] ),\n\t\t\t\t\t'name'    => sanitize_text_field( $theme['name'] ),\n\t\t\t\t\t'version' => sanitize_text_field( $theme['version'] ),\n\t\t\t\t\t'active'  => true === $theme['active'] ? 'yes' : 'no',\n\t\t\t\t);\n\t\t\t},\n\t\t\t$themes_data\n\t\t)"
      },
      "function": "get_themes_to_scan",
      "class": "PHP_Compatibility_Checker"
    },
    {
      "source": {
        "file": "lib/class-php-compatibility-checker.php",
        "line": 250,
        "kind": "sanitize_text_field",
        "category": "wordpress_input_functions",
        "expression": "sanitize_text_field( $theme['name'] )"
      },
      "sink": {
        "file": "lib/class-php-compatibility-checker.php",
        "line": 239,
        "kind": "array_filter",
        "category": "code_execution",
        "expression": "array_filter(\n\t\t\t$themes_data,\n\t\t\tfunction ( $theme_data ) use ( $excluded_themes ) {\n\t\t\t\treturn ! in_array( $theme_data['name'], $excluded_themes, true );\n\t\t\t}\n\t\t)"
      },
      "function": "get_themes_to_scan",
      "class": "PHP_Compatibility_Checker"
    },
    {
      "source": {
        "file": "lib/class-php-compatibility-checker.php",
        "line": 250,
        "kind": "sanitize_text_field",
        "category": "wordpress_input_functions",
        "expression": "sanitize_text_field( $theme['name'] )"
      },
      "sink": {
        "file": "lib/class-php-compatibility-checker.php",
        "line": 246,
        "kind": "array_map",
        "category": "code_execution",
        "expression": "array_map(\n\t\t\tfunction( $theme ) {\n\t\t\t\treturn array(\n\t\t\t\t\t'slug'    => sanitize_title( $theme['id'] ),\n\t\t\t\t\t'name'    => sanitize_text_field( $theme['name'] ),\n\t\t\t\t\t'version' => sanitize_text_field( $theme['version'] ),\n\t\t\t\t\t'active'  => true === $theme['active'] ? 'yes' : 'no',\n\t\t\t\t);\n\t\t\t},\n\t\t\t$themes_data\n\t\t)"
      },
      "function": "get_themes_to_scan",
      "class": "PHP_Compatibility_Checker"
    },
    {
      "source": {
        "file": "lib/class-php-compatibility-checker.php",
        "line": 251,
        "kind": "sanitize_text_field",
        "category": "wordpress_input_functions",
        "expression": "sanitize_text_field( $theme['version'] )"
      },
      "sink": {
        "file": "lib/class-php-compatibility-checker.php",
        "line": 239,
        "kind": "array_filter",
        "category": "code_execution",
        "expression": "array_filter(\n\t\t\t$themes_data,\n\t\t\tfunction ( $theme_data ) use ( $excluded_themes ) {\n\t\t\t\treturn ! in_array( $theme_data['name'], $excluded_themes, true );\n\t\t\t}\n\t\t)"
      },
      "function": "get_themes_to_scan",
      "class": "PHP_Compatibility_Checker"
    },
    {
      "source": {
        "file": "lib/class-php-compatibility-checker.php",
        "line": 251,
        "kind": "sanitize_text_field",
        "category": "wordpress_input_functions",
        "expression": "sanitize_text_field( $theme['version'] )"
      },
      "sink": {
        "file": "lib/class-php-compatibility-checker.php",
        "line": 246,
        "kind": "array_map",
        "category": "code_execution",
        "expression": "array_map(\n\t\t\tfunction( $theme ) {\n\t\t\t\treturn array(\n\t\t\t\t\t'slug'    => sanitize_title( $theme['id'] ),\n\t\t\t\t\t'name'    => sanitize_text_field( $theme['name'] ),\n\t\t\t\t\t'version' => sanitize_text_field( $theme['version'] ),\n\t\t\t\t\t'active'  => true === $theme['active'] ? 'yes' : 'no',\n\t\t\t\t);\n\t\t\t},\n\t\t\t$themes_data\n\t\t)"
      },
      "function": "get_themes_to_scan",
      "class": "PHP_Compatibility_Checker"
    }
  ],
  "errors": []
}